standwithcrypto
