Metadata-Version: 2.1
Name: standwithcrypto
Version: 0.0.2
Summary: Pull US politician data from standwithcrypto.org
Requires-Python: >=3.6
License-File: LICENSE
Requires-Dist: requests
